hyperion/__init__.py
hyperion/client.py
hyperion/const.py
hyperion/py.typed
hyperion_py-0.7.6.dist-info/LICENSE
hyperion_py-0.7.6.dist-info/METADATA
hyperion_py-0.7.6.dist-info/WHEEL
hyperion_py-0.7.6.dist-info/RECORD
