Metadata-Version: 2.3
Name: hyperion-py
Version: 0.7.6
Summary: Hyperion Ambient Lighting Python Package
License: MIT
Keywords: hyperion
Author: Dermot Duffy
Author-email: dermot.duffy@gmail.com
Requires-Python: >=3.8,<4.0
Classifier: Intended Audience :: Developers
Classifier: License :: OSI Approved :: MIT License
Classifier: Operating System :: OS Independent
Classifier: Programming Language :: Python :: 3
Classifier: Programming Language :: Python :: 3.8
Classifier: Programming Language :: Python :: 3.9
Classifier: Programming Language :: Python :: 3.10
Classifier: Programming Language :: Python :: 3.11
Classifier: Programming Language :: Python :: 3.12
Classifier: Programming Language :: Python :: 3.13
Classifier: Topic :: Home Automation
Project-URL: Repository, https://github.com/dermotduffy/hyperion-py
